python_guild/__init__.py
python_guild-1.0.1.dist-info/METADATA
python_guild-1.0.1.dist-info/WHEEL
python_guild-1.0.1.dist-info/RECORD
